AUTHORS
LICENSE
MANIFEST.in
README.rst
setup.py
python_sshtail.egg-info/PKG-INFO
python_sshtail.egg-info/SOURCES.txt
python_sshtail.egg-info/dependency_links.txt
python_sshtail.egg-info/not-zip-safe
python_sshtail.egg-info/requires.txt
python_sshtail.egg-info/top_level.txt
sshtail/__init__.py
sshtail/tailers.py
sshtail/utils.py