Metadata-Version: 1.0
Name: python-sshtail
Version: 0.0.2
Summary: Python classes to allow for tailing of multiple files via SSH.
Home-page: https://github.com/praekelt/python-sshtail
Author: Praekelt Foundation
Author-email: dev@praekelt.com
License: BSD
Platform: UNKNOWN
Classifier: Programming Language :: Python
Classifier: License :: OSI Approved :: BSD License
Classifier: Development Status :: 4 - Beta
Classifier: Operating System :: OS Independent
Classifier: Framework :: Django
Classifier: Intended Audience :: Developers
Classifier: Topic :: Internet :: WWW/HTTP :: Dynamic Content
